{
    "tables": [
        {
            "name": "pokemon_found_out475",
            "pokemon": [
                {
                    "species": "MONSTER_VENONAT",
                    "level": 17,
                    "probability": 3333
                },
                {
                    "species": "MONSTER_AIPOM",
                    "level": 15,
                    "probability": 3334
                },
                {
                    "species": "MONSTER_SEEDOT",
                    "level": 16,
                    "probability": 3333
                },
                {
                    "species": "MONSTER_KECLEON",
                    "level": 90,
                    "probability": 0
                },
                {
                    "species": "MONSTER_DECOY",
                    "level": 1,
                    "probability": 0
                }
            ]
        },
        {
            "name": "pokemon_found_out476",
            "pokemon": [
                {
                    "species": "MONSTER_VENONAT",
                    "level": 17,
                    "probability": 2500
                },
                {
                    "species": "MONSTER_AIPOM",
                    "level": 15,
                    "probability": 2500
                },
                {
                    "species": "MONSTER_SEEDOT",
                    "level": 16,
                    "probability": 2500
                },
                {
                    "species": "MONSTER_ROSELIA",
                    "level": 16,
                    "probability": 2500
                },
                {
                    "species": "MONSTER_KECLEON",
                    "level": 90,
                    "probability": 0
                },
                {
                    "species": "MONSTER_DECOY",
                    "level": 1,
                    "probability": 0
                }
            ]
        },
        {
            "name": "pokemon_found_out477",
            "pokemon": [
                {
                    "species": "MONSTER_VENONAT",
                    "level": 17,
                    "probability": 2353
                },
                {
                    "species": "MONSTER_AIPOM",
                    "level": 15,
                    "probability": 2353
                },
                {
                    "species": "MONSTER_SEEDOT",
                    "level": 16,
                    "probability": 2353
                },
                {
                    "species": "MONSTER_NUZLEAF",
                    "level": 10,
                    "probability": 588
                },
                {
                    "species": "MONSTER_ROSELIA",
                    "level": 16,
                    "probability": 2353
                },
                {
                    "species": "MONSTER_KECLEON",
                    "level": 90,
                    "probability": 0
                },
                {
                    "species": "MONSTER_DECOY",
                    "level": 1,
                    "probability": 0
                }
            ]
        },
        {
            "name": "pokemon_found_out478",
            "pokemon": [
                {
                    "species": "MONSTER_AIPOM",
                    "level": 15,
                    "probability": 3077
                },
                {
                    "species": "MONSTER_SEEDOT",
                    "level": 16,
                    "probability": 3077
                },
                {
                    "species": "MONSTER_NUZLEAF",
                    "level": 10,
                    "probability": 769
                },
                {
                    "species": "MONSTER_ROSELIA",
                    "level": 16,
                    "probability": 3077
                },
                {
                    "species": "MONSTER_KECLEON",
                    "level": 90,
                    "probability": 0
                },
                {
                    "species": "MONSTER_DECOY",
                    "level": 1,
                    "probability": 0
                }
            ]
        },
        {
            "name": "pokemon_found_out479",
            "pokemon": [
                {
                    "species": "MONSTER_SEEDOT",
                    "level": 16,
                    "probability": 4444
                },
                {
                    "species": "MONSTER_NUZLEAF",
                    "level": 10,
                    "probability": 1112
                },
                {
                    "species": "MONSTER_ROSELIA",
                    "level": 16,
                    "probability": 4444
                },
                {
                    "species": "MONSTER_KECLEON",
                    "level": 90,
                    "probability": 0
                },
                {
                    "species": "MONSTER_DECOY",
                    "level": 1,
                    "probability": 0
                }
            ]
        },
        {
            "name": "pokemon_found_out480",
            "pokemon": [
                {
                    "species": "MONSTER_MANKEY",
                    "level": 11,
                    "probability": 4444
                },
                {
                    "species": "MONSTER_SEEDOT",
                    "level": 16,
                    "probability": 4445
                },
                {
                    "species": "MONSTER_NUZLEAF",
                    "level": 10,
                    "probability": 1111
                },
                {
                    "species": "MONSTER_KECLEON",
                    "level": 90,
                    "probability": 0
                },
                {
                    "species": "MONSTER_DECOY",
                    "level": 1,
                    "probability": 0
                }
            ]
        }
    ]
}